pyTwistyScrambler/__init__.py
pyTwistyScrambler/bigCubesScrambler.py
pyTwistyScrambler/clockScrambler.py
pyTwistyScrambler/cuboidsScrambler.py
pyTwistyScrambler/ftoScrambler.py
pyTwistyScrambler/megaminxScrambler.py
pyTwistyScrambler/miscScrambler.py
pyTwistyScrambler/pyraminxScrambler.py
pyTwistyScrambler/rexScrambler.py
pyTwistyScrambler/scrambler222.py
pyTwistyScrambler/scrambler333.py
pyTwistyScrambler/scrambler444.py
pyTwistyScrambler/scrambler555.py
pyTwistyScrambler/scrambler666.py
pyTwistyScrambler/scrambler777.py
pyTwistyScrambler/skewbScrambler.py
pyTwistyScrambler/squareOneScrambler.py
pyTwistyScrambler/js_resources/1x3x3.js
pyTwistyScrambler/js_resources/2x2x2.js
pyTwistyScrambler/js_resources/2x2x3.js
pyTwistyScrambler/js_resources/cross.js
pyTwistyScrambler/js_resources/fto.js
pyTwistyScrambler/js_resources/mathlib.js
pyTwistyScrambler/js_resources/megascramble.js
pyTwistyScrambler/js_resources/pyraminx.js
pyTwistyScrambler/js_resources/scramble.js
pyTwistyScrambler/js_resources/scramble_333_edit.js
pyTwistyScrambler/js_resources/scramble_444.js
pyTwistyScrambler/js_resources/scramble_sq1.js
pyTwistyScrambler/js_resources/skewb.js
pyTwistyScrambler/js_resources/utilscramble.js
pyTwistyScrambler-1.7.dist-info/LICENSE
pyTwistyScrambler-1.7.dist-info/METADATA
pyTwistyScrambler-1.7.dist-info/WHEEL
pyTwistyScrambler-1.7.dist-info/top_level.txt
pyTwistyScrambler-1.7.dist-info/RECORD
