Metadata-Version: 2.1
Name: pyTwistyScrambler
Version: 1.7
Summary: A Python utility package for generating scrambles for twisty puzzles
Home-page: https://github.com/euphwes/pyTwistyScrambler
Author: euphwes
Author-email: euphwes@gmail.com
Project-URL: Bug Tracker, https://github.com/euphwes/pyTwistyScrambler/issues
License-File: LICENSE
Requires-Dist: appdirs
Requires-Dist: packaging
Requires-Dist: PyExecJS
Requires-Dist: pyparsing
Requires-Dist: six
